misc/smalldseddr1/vivado/u2p/rw-add2-np3/src/profCounter/FIFO/SyncRAMSimpleDualPort.v
`timescale 1ns / 1ps

module SyncRAMSimpleDualPort#(
	parameter ADDR_WIDTH = 16,
	parameter DATA_WIDTH = 32
) (
	/* Standard pins */
	clk,

	/* Port A */
	enA,
	writeA,
	addressA,
	writeDataA,
	/* Port B */
	enB,
	addressB,
	readDataB
);

	input clk;

	input enA;
	input writeA;
	input [ADDR_WIDTH-1:0] addressA;
	input [DATA_WIDTH-1:0] writeDataA;
	input enB;
	input [ADDR_WIDTH-1:0] addressB;
	output [DATA_WIDTH-1:0] readDataB;

	reg [DATA_WIDTH-1:0] mem [0:(1 << ADDR_WIDTH)-1];
	reg [DATA_WIDTH-1:0] intReadDataB;

	assign readDataB = intReadDataB;

	always @(posedge clk) begin
		if(enA && writeA)
			mem[addressA] <= writeDataA;
	end

	always @(posedge clk) begin
		if(enB)
			intReadDataB <= mem[addressB];
	end

endmodule

misc/smalldseddr1/vivado/U2p/rw-add2-np/src/profCounter/FIFO/FIFO.v
`define CLOG2(x) (\
	(x <= 2)? 1 :\
	(x <= 4)? 2 :\
	(x <= 8)? 3 :\
	(x <= 16)? 4 :\
	(x <= 32)? 5 :\
	(x <= 64)? 6 :\
	(x <= 128)? 7 :\
	(x <= 256)? 8 :\
	(x <= 512)? 9 :\
	(x <= 1024)? 10 :\
	-1\
)

module FIFO#(
	parameter SIZE = 16,
	parameter DATA_WIDTH = 32
) (
	/* Standard pins */
	clk,
	rst_n,

	/* FIFO commands */
	enqueue,
	dequeue,
	/* FIFO input */
	back,
	/* FIFO output */
	front,
	/* Status signals */
	full,
	empty
);

	input clk;
	input rst_n;

	input enqueue;
	input dequeue;
	input [DATA_WIDTH-1:0] back;
	output [DATA_WIDTH-1:0] front;
	output full;
	output empty;

	reg [`CLOG2(SIZE)-1:0] backPointer;
	reg [`CLOG2(SIZE)-1:0] frontPointer;
	reg [`CLOG2(SIZE):0] occupied;
	reg rawDetected;
	reg [DATA_WIDTH-1:0] rawReg;
	wire [DATA_WIDTH-1:0] ramReadData;
	wire commitEnqueue;
	wire commitDequeue;
	wire [`CLOG2(SIZE)-1:0] frontPointerNow;

	assign front = rawDetected? rawReg : ramReadData;
	assign full = SIZE == occupied;
	assign empty = 'h0 == occupied;

	/* Enqueue only happens when FIFO is not full */
	assign commitEnqueue = enqueue && !full;
	/* Dequeue only happens when FIFO is not empty */
	assign commitDequeue = dequeue && !empty;
	/* The "now" signal masks the registered output latency from the RAM */
	assign frontPointerNow = commitDequeue? (((SIZE - 'h1) == frontPointer)? 'h0 : (frontPointer + 'h1)) : frontPointer;

	/* Simple dual-port synchronous memory */
	SyncRAMSimpleDualPort#(`CLOG2(SIZE), DATA_WIDTH) ram(
		.clk(clk),

		/* Port A is FIFO input */
		.enA(1'b1),
		.writeA(commitEnqueue),
		.addressA(backPointer),
		.writeDataA(back),

		/* Port B is FIFO output */
		.enB(1'b1),
		.addressB(frontPointerNow),
		.readDataB(ramReadData)
	);

	always @(posedge clk) begin
		if(!rst_n) begin
			backPointer <= 'h0;
			frontPointer <= 'h0;
			occupied <= 'h0;
			rawDetected <= 1'b0;
			rawReg <= 'h0;
		end
		else begin
			/* Update pointers */
			if(commitEnqueue)
				backPointer <= ((SIZE - 'h1) == backPointer)? 'h0 : (backPointer + 'h1);
			if(commitDequeue)
				frontPointer <= frontPointerNow;

			/* Occupied does not change if nothing happens or if simultaneous enqueue/dequeue happens */
			if(commitEnqueue && !commitDequeue)
				occupied <= occupied + 'h1;
			else if(!commitEnqueue && commitDequeue)
				occupied <= occupied - 'h1;

			/* We want the memory to work as a read-after-write logic (e.g. when addressA and addressB matches) */
			/* Thus when this happens, we save this state, so that the next clock the output will be concise */
			if(commitEnqueue && (frontPointerNow == backPointer)) begin
				rawDetected <= 1'b1;
				rawReg <= back;
			end
			else begin
				rawDetected <= 1'b0;
			end
		end
	end

endmodule

misc/smalldseddr1/vivado/-/rw-add2/src/profCounter/FIFO/tb/tb.v
`timescale 1ns / 1ps

module tb;

	reg clk;
	reg rst_n;

	reg enqueue;
	reg dequeue;
	reg [7:0] back;
	wire [7:0] front;
	wire full;
	wire empty;

	/* DUT */
	FIFO#(4, 8) inst(
		.clk(clk),
		.rst_n(rst_n),

		.enqueue(enqueue),
		.dequeue(dequeue),
		.back(back),
		.front(front),
		.full(full),
		.empty(empty)
	);

	initial begin
		$dumpfile("tb.vcd");
		$dumpvars(1, clk, rst_n, enqueue, dequeue, back, front, full, empty);

		/* Reset */
		clk <= 'b1;
		rst_n <= 'b0;
		enqueue <= 'b0;
		dequeue <= 'b0;
		back <= 'h00;
		#200 @(posedge clk);

		/* Release reset */
		rst_n <= 'b1;
		#200 @(posedge clk);

		/* FRONT [  |  |  |  ] BACK */

		/* Enqueue some elements */
		enqueue <= 'b1;
		back <= 'hDE;
		#50 @(posedge clk);
		back <= 'hAD;
		#50 @(posedge clk);

		/* FRONT [DE|AD|  |  ] BACK */

		/* Dequeue one element */
		enqueue <= 'b0;
		dequeue <= 'b1;
		#50 @(posedge clk);

		/* FRONT [AD|  |  |  ] BACK */

		/* Fill the FIFO */
		enqueue <= 'b1;
		dequeue <= 'b0;
		back <= 'hAE;
		#50 @(posedge clk);
		back <= 'hCA;
		#50 @(posedge clk);
		back <= 'hFE;
		#50 @(posedge clk);
		back <= 'hAA;
		#50 @(posedge clk);
		back <= 'hBB;
		#50 @(posedge clk);
		back <= 'hCC;
		#50 @(posedge clk);
		back <= 'hDD;
		#50 @(posedge clk);

		/* FRONT [AD|AE|CA|FE] BACK */

		/* Dequeue all elements */
		enqueue <= 'b0;
		dequeue <= 'b1;
		#400 @(posedge clk);

		/* FRONT [  |  |  |  ] BACK */

		/* Insert one element */
		enqueue <= 'b1;
		dequeue <= 'b0;
		back <= 'hAB;
		#50 @(posedge clk);

		/* FRONT [AB|  |  |  ] BACK */

		/* Simultaneosly enqueue/dequeue */
		enqueue <= 'b1;
		dequeue <= 'b1;
		back <= 'hCD;
		#50 @(posedge clk);

		/* FRONT [CD|  |  |  ] BACK */

		/* Fill the FIFO */
		enqueue <= 'b1;
		dequeue <= 'b0;
		back <= 'hAD;
		#50 @(posedge clk);
		back <= 'hCA;
		#50 @(posedge clk);
		back <= 'hFE;
		#50 @(posedge clk);
		back <= 'hAA;
		#50 @(posedge clk);
		back <= 'hBB;
		#50 @(posedge clk);
		back <= 'hCC;
		#50 @(posedge clk);
		back <= 'hDD;
		#50 @(posedge clk);

		/* FRONT [CD|AD|CA|FE] BACK */

		/* Simultaneosly enqueue/dequeue (enqueue won't work as the FIFO is full) */
		enqueue <= 'b1;
		dequeue <= 'b1;
		back <= 'hEF;
		#50 @(posedge clk);

		/* FRONT [AD|CA|FE|  ] BACK */

		/* Dequeue two elements */
		enqueue <= 'b0;
		dequeue <= 'b1;
		#200 @(posedge clk);

		/* FRONT [FE|  |  |  ] BACK */

		/* Simultaneosly enqueue/dequeue */
		enqueue <= 'b1;
		dequeue <= 'b1;
		back <= 'hAE;
		#50 @(posedge clk);

		/* FRONT [AE|  |  |  ] BACK */

		/* Clean FIFO and finish */
		enqueue <= 'b0;
		dequeue <= 'b1;
		#400 @(posedge clk);

		/* FRONT [  |  |  |  ] BACK */

		$finish;
	end

	always begin
		#50 clk <= ~clk;
	end

endmodule

misc/smalldseddr1/vivado/-/rw-seq2/src/profCounter/FIFO/tb/tb.unr.old.vcd
$date
	Mon Mar 25 20:38:04 2019
$end
$version
	Icarus Verilog
$end
$timescale
	1ps
$end
$scope module tb $end
$var reg 1 ! clk $end
$upscope $end
$scope module tb $end
$var reg 1 " rst_n $end
$upscope $end
$scope module tb $end
$var reg 1 # enqueue $end
$upscope $end
$scope module tb $end
$var reg 1 $ dequeue $end
$upscope $end
$scope module tb $end
$var reg 8 % back [7:0] $end
$upscope $end
$scope module tb $end
$var wire 8 & front [7:0] $end
$upscope $end
$scope module tb $end
$var wire 1 ' full $end
$upscope $end
$scope module tb $end
$var wire 1 ( empty $end
$upscope $end
$enddefinitions $end
#0
$dumpvars
1(
0'
bx &
b0 %
0$
0#
0"
1!
$end
#50000
0!
#100000
1!
#150000
0!
#200000
1"
1!
#250000
0!
#300000
1!
#350000
0!
#400000
b11011110 %
1#
1!
#450000
0!
#500000
0(
b11011110 &
b10101101 %
1!
#550000
0!
#600000
1$
0#
1!
#650000
0!
#700000
b10101101 &
b10101110 %
0$
1#
1!
#750000
0!
#800000
b11001010 %
1!
#850000
0!
#900000
b11111110 %
1!
#950000
0!
#1000000
1'
b10101010 %
1!
#1050000
0!
#1100000
b10111011 %
1!
#1150000
0!
#1200000
b11001100 %
1!
#1250000
0!
#1300000
b11011101 %
1!
#1350000
0!
#1400000
1$
0#
1!
#1450000
0!
#1500000
0'
b10101110 &
1!
#1550000
0!
#1600000
b11001010 &
1!
#1650000
0!
#1700000
b11111110 &
1!
#1750000
0!
#1800000
1(
b10101101 &
b10101011 %
0$
1#
1!
#1850000
0!
#1900000
0(
b10101011 &
b11001101 %
1$
1!
#1950000
0!
#2000000
b11001101 &
b10101101 %
0$
1!
#2050000
0!
#2100000
b11001010 %
1!
#2150000
0!
#2200000
b11111110 %
1!
#2250000
0!
#2300000
1'
b10101010 %
1!
#2350000
0!
#2400000
b10111011 %
1!
#2450000
0!
#2500000
b11001100 %
1!
#2550000
0!
#2600000
b11011101 %
1!
#2650000
0!
#2700000
b11101111 %
1$
1!
#2750000
0!
#2800000
b10101101 &
0#
1!
#2850000
0!
#2900000
0'
b11001010 &
1!
#2950000
0!
#3000000
b11111110 &
b10101110 %
1#
1!
#3050000
0!
#3100000
b11101111 &
0#
1!
#3150000
0!
#3200000
b10101110 &
1!
#3250000
0!
#3300000
1(
b11001010 &
1!
